distclassipy/__init__.py
distclassipy/classifier.py
distclassipy/distances.py
distclassipy-0.2.1.dist-info/LICENSE
distclassipy-0.2.1.dist-info/METADATA
distclassipy-0.2.1.dist-info/WHEEL
distclassipy-0.2.1.dist-info/top_level.txt
distclassipy-0.2.1.dist-info/RECORD
