Metadata-Version: 2.1
Name: distclassipy
Version: 0.2.1
Summary: A python package for a distance-based classifier which can use several different distance metrics.
Author-email: Siddharth Chaini <sidchaini@gmail.com>
License: GNU GENERAL PUBLIC LICENSE
Project-URL: Repository, https://github.com/sidchaini/DistClassiPy
Project-URL: Documentation, https://sidchaini.github.io/DistClassiPy/
Classifier: Development Status :: 4 - Beta
Classifier: Intended Audience :: Developers
Classifier: Intended Audience :: Education
Classifier: Intended Audience :: Science/Research
Classifier: License :: OSI Approved :: GNU General Public License v3 (GPLv3)
Classifier: Programming Language :: Python :: 3.10
Classifier: Programming Language :: Python :: 3.11
Classifier: Programming Language :: Python :: 3.12
Classifier: Programming Language :: Python :: 3.13
Classifier: Operating System :: OS Independent
Requires-Python: >=3.10
License-File: LICENSE
Requires-Dist: joblib>=1.3.2
Requires-Dist: numpy>=1.25.2
Requires-Dist: pandas>=2.0.3
Requires-Dist: scikit-learn>=1.2.2
